jupview.py
jupview-0.0.2.data/scripts/jupview
jupview-0.0.2.dist-info/METADATA
jupview-0.0.2.dist-info/WHEEL
jupview-0.0.2.dist-info/top_level.txt
jupview-0.0.2.dist-info/RECORD
