Metadata-Version: 2.1
Name: jupview
Version: 0.0.2
Summary: Simple terminal jupyter notebook viewer
Home-page: https://github.com/artiomio/sampleproject
Author: Artiom Peysahovsky
Author-email: peysahovsky@gmail.com
License: UNKNOWN
Platform: UNKNOWN
Classifier: Programming Language :: Python :: 3
Classifier: License :: OSI Approved :: MIT License
Classifier: Operating System :: Unix
Classifier: Environment :: Console
Requires-Python: >=3.6
